google_reauth/__init__.py
google_reauth/_helpers.py
google_reauth/_reauth_client.py
google_reauth/challenges.py
google_reauth/errors.py
google_reauth/reauth.py
google_reauth/reauth_creds.py
google_reauth-0.1.0.dist-info/DESCRIPTION.rst
google_reauth-0.1.0.dist-info/METADATA
google_reauth-0.1.0.dist-info/RECORD
google_reauth-0.1.0.dist-info/WHEEL
google_reauth-0.1.0.dist-info/metadata.json
google_reauth-0.1.0.dist-info/top_level.txt
